[
  {
    "id": "the-beginning-of-infinity",
    "title": "The Beginning of Infinity",
    "author": "David Deutsch",
    "color": "#5078B0",
    "cover": "./assets/books/infinity.jpg",
    "review": "the-beginning-of-infinity.md"
  },
  {
    "id": "the-art-of-doing-science-and-engineering",
    "title": "The Art of Doing Science and Engineering",
    "author": "Richard W. Hamming",
    "color": "#6AA06E",
    "cover": "./assets/books/hamming.jpg",
    "review": "the-art-of-doing-science-and-engineering.md"
  },
  {
    "id": "americanah",
    "title": "Americanah",
    "author": "Chimamanda Ngozi Adichie",
    "color": "#8C664E",
    "cover": "./assets/books/americanah.jpg",
    "review": "americanah.md"
  },
  {
    "id": "stoner",
    "title": "Stoner",
    "author": "John Williams",
    "color": "#8C664E",
    "cover": "./assets/books/stoner.jpg",
    "review": "stoner.md"
  }
]